ustb_sso/__init__.py
ustb_sso/_data.py
ustb_sso/_exceptions.py
ustb_sso/_prefabs.py
ustb_sso/_procedure.py
ustb_sso/_sessions.py
ustb_sso-1.3.0.dist-info/LICENSE
ustb_sso-1.3.0.dist-info/METADATA
ustb_sso-1.3.0.dist-info/WHEEL
ustb_sso-1.3.0.dist-info/RECORD
