Metadata-Version: 2.3
Name: USTB-SSO
Version: 1.3.0
Summary: USTB Single Sign-On Authentication Library
License: MIT
Author: Harry Huang
Author-email: harryhuang2652@qq.com
Requires-Python: >=3.8,<4
Classifier: Programming Language :: Python :: 3
Classifier: License :: OSI Approved :: MIT License
Classifier: Operating System :: OS Independent
Provides-Extra: httpx
Requires-Dist: httpx (>=0.28,<1.0) ; extra == "httpx"
Requires-Dist: no-puzzle-captcha (>=1.1.0,<1.2.0)
